src/rtl/branch_comparator.v
module branch_comparator (
    input wire[31:0] data_1,
    input wire[31:0] data_2,
    input wire[31:0] instruction,
    input wire branch_control,
    output reg branch_decision
);

wire[2:0] funct3 = instruction[14:12];

always @(*) begin
    if (branch_control) begin
        case (funct3)
            3'b000: begin
                branch_decision = (data_1 == data_2);
            end
            3'b001: begin
                branch_decision = (data_1 != data_2);
            end
            3'b100: begin
                branch_decision = ($signed(data_1) < $signed(data_2));
            end
            3'b101: begin
                branch_decision = ($signed(data_1) >= $signed(data_2)); 
            end
            3'b110: begin
                branch_decision = (data_1 < data_2); 
            end
            3'b111: begin
                branch_decision = (data_1 >= data_2); 
            end
            default: begin
                branch_decision = 1'b0;
            end
        endcase
    end else begin
        branch_decision = 1'b0;
    end
end

endmodule

src/d_memory.v
module d_memory (
    input wire clock,
    input wire memory_write,
    input wire memory_read,
    input wire[31:0] address,
    input wire[31:0] data_write,
    output wire[31:0] data_read
);

reg [31:0] ram [0:255]; // Roughly 1 KB
integer i;

initial begin
    for (i = 0; i < 256; i = i + 1) begin
        ram[i] = 32'b0;
    end
end

always @(posedge clock) begin
    if (memory_write) begin
        ram[address[31:2]] <= data_write;
    end
end

assign data_read = (memory_read) ? ram[address[31:2]] : 32'b0;

endmodule

src/alu.v
module alu (
    input wire[31:0] in_1,
    input wire[31:0] in_2,
    input wire[3:0] control,
    output reg[31:0] out
);

always @(*) begin
    case (control)
        4'b0000: begin // ADD
            out = in_1 + in_2;
        end
        4'b0001: begin // SUB
            out = in_1 - in_2;
        end
        4'b0010: begin // SLL
            out = in_1 << in_2[4:0];
        end
        4'b0011: begin // SLT
            out = ($signed(in_1) < $signed(in_2)) ? 1 : 0;
        end
        4'b0100: begin // SLTU
            out = (in_1 < in_2) ? 1 : 0;
        end
        4'b0101: begin // XOR
            out = in_1 ^ in_2;
        end
        4'b0110: begin // OR
            out = in_1 | in_2;
        end
        4'b0111: begin // AND
            out = in_1 & in_2;
        end
        4'b1000: begin // SRL
            out = in_1 >> in_2[4:0];
        end
        4'b1001: begin // SRA
            out = $signed(in_1) >>> in_2[4:0];
        end
        default: begin // Default
            out = 32'b0;
        end

    endcase
end

endmodule

src/alu_control.v
module alu_control (
    input wire[1:0] alu_operation, // Operation type Identifier
    input wire[31:0] instruction,
    output reg[3:0] alu_control_out // ALU Control 
);

wire funct3[2:0] = instruction[14:12];
wire funct7_30b = instruction[30];

always @(*) begin
    case (alu_operation)
        2'b00: begin // Memory Access
            alu_control_out = 4'b0000; 
        end 
        2'b01: begin // Branching
            alu_control_out = 4'b0001; 
        end
        2'b10: begin // Arithmetic
            case (funct3)
                3'b000: alu_control_out = (funct7_30b) ? 4'b0001 : 4'b0000; 
                3'b001: alu_control_out = 4'b0010; // SLL
                3'b010: alu_control_out = 4'b0011; // SLT
                3'b011: alu_control_out = 4'b0100; // SLTU
                3'b100: alu_control_out = 4'b0101; // XOR
                3'b101: alu_control_out = 4'b0110; // OR
                3'b110: alu_control_out = 4'b0110; // AND
                3'b111: alu_control_out = (funct7_30b) ? 4'b1000 : 4'b1001; 
                default: alu_control_out = 4'b0000;
            endcase
        end
        2'b11: begin
            case (funct3)
                3'b000: alu_control_out = 4'b0000; // ADDI
                3'b001: alu_control_out = 4'b0010; // SLLI
                3'b010: alu_control_out = 4'b0011; // SLTI
                3'b011: alu_control_out = 4'b0100; // SLTIU
                3'b100: alu_control_out = 4'b0101; // XORI
                3'b101: alu_control_out = 4'b0110; // ORI
                3'b110: alu_control_out = 4'b0110; // ANDI
                3'b111: begin
                    case (instruction[19])
                        3'b1: alu_control_out = 4'b1001; // SRAI
                        3'b0: alu_control_out = 4'b1000; // SRLI
                    endcase
                end  
                default: alu_control_out = 4'b0000;
            endcase
        end
        default: begin
            alu_control_out = 4'b0000;
        end
    endcase
end

endmodule

src/rtl/main.v
module main (
    input wire[6:0] opcode,
    output reg branch,
    output reg memory_read,
    output reg memory_register,
    output reg[1:0] alu_operation,
    output reg memory_write,
    output reg alu_source,
    output reg register_write
);

always @(*) begin
    case (opcode)
        7'b0110011: begin // R-type
            branch = 1'b0;
            memory_read = 1'b0;
            memory_register = 1'b0;
            alu_operation = 2'b10;
            memory_write = 1'b0;
            alu_source = 1'b0;
            register_write = 1'b1;
        end 
        7'b0010011: begin // I-type
            branch = 1'b0;
            memory_read = 1'b0;
            memory_register = 1'b0;
            alu_operation = 2'b11;
            memory_write = 1'b0;
            alu_source = 1'b1;
            register_write = 1'b1;
        end 
        7'b0000011: begin // lw
            branch = 1'b0;
            memory_read = 1'b1;
            memory_register = 1'b1;
            alu_operation = 2'b00;
            memory_write = 1'b0;
            alu_source = 1'b1;
            register_write = 1'b1;
        end 
        7'b0100011: begin // sw
            branch = 1'b0;
            memory_read = 1'b0;
            memory_register = 1'b0;
            alu_operation = 2'b00;
            memory_write = 1'b1;
            alu_source = 1'b1;
            register_write = 1'b0;
        end 
        7'b1100011: begin // Branching
            branch = 1'b1;
            memory_read = 1'b0;
            memory_register = 1'b0;
            alu_operation = 2'b01;
            memory_write = 1'b0;
            alu_source = 1'b0;
            register_write = 1'b0;
        end 
        default: begin // 
            branch = 1'b0;
            memory_read = 1'b0;
            memory_register = 1'b0;
            alu_operation = 2'b00;
            memory_write = 1'b0;
            alu_source = 1'b0;
            register_write = 1'b0;
        end 
        
    endcase
end

endmodule

immediate.v
module immediate (
    input wire[31:0] instruction,
    output reg[31:0] immediate_out
);

wire [6:0] opcode = instruction[6:0];

always @(*) begin
    case (opcode)

end
endmodule

src/rtl/register.v
module register (
    input wire write_enable,
    input wire clock,
    input wire[31:0] instruction,
    input wire[31:0] data_in,
    output wire[31:0] data_1,
    output wire[31:0] data_2
);

wire[4:0] add_1 = instruction[19:15];
wire[4:0] add_2 = instruction[24:20];
wire[4:0] dest_add = instruction[11:7];


reg [31:0] registers [0:31]; // Create register array
integer i;
initial begin // Fill registers
    for (i = 0; i < 32; i = i + 1) begin
        registers[i] = 32'b0; 
    end
end

assign data_1 = (add_1 == 5'b00000) ? 32'b0 : registers[add_1]; // Check for x0 read
assign data_2 = (add_2 == 5'b00000) ? 32'b0 : registers[add_2]; // Check for x0 read

always @(posedge clock) begin
    if (write_enable && (dest_add != 5'b00000)) begin
        registers[dest_add] <= data_in; // Write Data
    end
end



endmodule

RV32I/src/rtl/i_memory.v
module i_memory (
    input wire[31:0] pc_in,
    output wire[31:0] instruction
);

reg [31:0] rom [0:255];

integer i;

initial begin
    for (i = 0; i < 256; i = i + 1) begin
        rom[i] <= 32'b0;
    end
end

assign instruction = rom[pc_in[31:2]];

endmodule

src/pc_adder.v
module pc_adder (
    input wire[31:0] add_in,
    output wire[31:0] add_out
);

    assign add_out = add_in + 32'd4;

endmodule

src/pc_reg.v
module pc_register (
    input wire clock,
    input wire reset, 
    input wire[31:0] pc_in, // PC MUX Output
    output reg[31:0] pc_out // Program Count
);

always @(posedge clock) begin
    if (reset) begin
        pc_out <= 32'b0; // Set Program Count to 32'b0
    end else begin
        pc_out <= pc_in; // Set Program Count to PC MUX Output
    end
end 

endmodule

src/core.v
module core(
    input wire clock,
    input wire reset,
    output wire [31:0] output_core
);
    wire[31:0] pc;
    wire[31:0] pc_mux;
    wire[31:0] pc_next;
    wire[31:0] pc_branch;
    wire[31:0] instruction;
    
    wire branch;
    wire memory_read;
    wire memory_register;
    wire memory_write;
    wire alu_source;
    wire register_write;
    wire[1:0] alu_operation;
    wire[3:0] alu_control;
    wire[31:0] rs1;
    wire[31:0] rs2;
    wire[31:0] register_mux;
    wire[31:0] immediate;
    wire[31:0] alu_input_mux;
    wire[31:0] alu_output;
    wire[31:0] data_memory_read;

    wire alu_zero = (alu_output == 32'b0);
    wire branch_decision;

assign pc_mux = (branch_decision) ? pc_branch : pc_next;

assign alu_input_mux = (alu_source) ? immediate : rs2;

assign register_mux = (memory_register) ? data_memory_read : alu_output;

assign pc_branch = pc + immediate;

pc_register pc_reg (
    .clock(clock),
    .reset(reset),
    .pc_in(pc_mux),
    .pc_out(pc)
);

pc_adder pc_adder (
    .add_in(pc),
    .add_out(pc_next)
);

i_memory i_memory (
    .pc_in(pc),
    .instruction(instruction)
);

register register (
    .write_enable(register_write),
    .clock(clock),
    .instruction(instruction),
    .data_in(register_mux),
    .data_1(rs1),
    .data_2(rs2)
);

immediate immediate_module (
    .instruction(instruction),
    .immediate_out(immediate)
);

main main (
    .opcode(instruction[6:0]),
    .branch(branch),
    .memory_read(memory_read),
    .memory_register(memory_register),
    .alu_operation(alu_operation),
    .memory_write(memory_write),
    .alu_source(alu_source),
    .register_write(register_write)
);

alu_control alu_cont (
    .alu_operation(alu_operation),
    .instruction(instruction),
    .alu_control_out(alu_control)
);

alu alu (
    .in_1(rs1),
    .in_2(alu_input_mux),
    .control(alu_control),
    .out(alu_output)
);

d_memory d_memory (
    .clock(clock),
    .memory_write(memory_write),
    .memory_read(memory_read),
    .address(alu_output),
    .data_write(rs2),
    .data_read(data_memory_read)
);

branch_comparator branch_comparator (
    .data_1(rs1),
    .data_2(rs2),
    .instruction(instruction),
    .branch_control(branch),
    .branch_decision(branch_decision)
);


endmodule

src/core_tb.v
`timescale 1ns / 1ps

module core_tb;
    reg clock;
    reg reset;
    wire[31:0] core_output;
    
    core uut (
        .clock(clock),
        .reset(reset),
        .output_core(core_output)
    );
    

initial begin
    clock = 0;
    forever #5 clock = ~clock;
end

initial begin
    begin
        $monitor("%0t | %h | %d", $time, uut.instruction, uut.alu_output);
        uut.i_memory.rom[0] = 32'00000000001000001000000110110011;
        reset = 1;
        #20;
        reset = 0;
        #1000;
        $display("Finished");    
        $finish;
    end
end


endmodule

src/tb/mcu_simulation.vcd
$date
	Wed Jul  1 23:45:51 2026
$end
$version
	Icarus Verilog
$end
$timescale
	1ps
$end
$scope module core_tb $end
$var wire 32 ! core_output [31:0] $end
$var reg 1 " clock $end
$var reg 1 # reset $end
$scope module uut $end
$var wire 1 " clock $end
$var wire 32 $ output_core [31:0] $end
$var wire 1 # reset $end
$var wire 32 % rs2 [31:0] $end
$var wire 32 & rs1 [31:0] $end
$var wire 1 ' register_write $end
$var wire 32 ( register_mux [31:0] $end
$var wire 32 ) pc_next [31:0] $end
$var wire 32 * pc_mux [31:0] $end
$var wire 32 + pc_branch [31:0] $end
$var wire 32 , pc [31:0] $end
$var wire 1 - memory_write $end
$var wire 1 . memory_register $end
$var wire 1 / memory_read $end
$var wire 32 0 instruction [31:0] $end
$var wire 32 1 immediate [31:0] $end
$var wire 32 2 data_memory_read [31:0] $end
$var wire 1 3 branch_decision $end
$var wire 1 4 branch $end
$var wire 1 5 alu_zero $end
$var wire 1 6 alu_source $end
$var wire 32 7 alu_output [31:0] $end
$var wire 2 8 alu_operation [1:0] $end
$var wire 32 9 alu_input_mux [31:0] $end
$var wire 4 : alu_control [3:0] $end
$scope module alu $end
$var wire 32 ; in_2 [31:0] $end
$var wire 32 < in_1 [31:0] $end
$var wire 4 = control [3:0] $end
$var reg 32 > out [31:0] $end
$upscope $end
$scope module alu_cont $end
$var wire 32 ? instruction [31:0] $end
$var wire 1 @ funct7_30b $end
$var wire 3 A funct3 [2:0] $end
$var wire 2 B alu_operation [1:0] $end
$var reg 4 C alu_control_out [3:0] $end
$upscope $end
$scope module branch_comparator $end
$var wire 32 D instruction [31:0] $end
$var wire 3 E funct3 [2:0] $end
$var wire 32 F data_2 [31:0] $end
$var wire 32 G data_1 [31:0] $end
$var wire 1 4 branch_control $end
$var reg 1 3 branch_decision $end
$upscope $end
$scope module d_memory $end
$var wire 32 H address [31:0] $end
$var wire 1 " clock $end
$var wire 1 - memory_write $end
$var wire 1 / memory_read $end
$var wire 32 I data_write [31:0] $end
$var wire 32 J data_read [31:0] $end
$var integer 32 K i [31:0] $end
$upscope $end
$scope module i_memory $end
$var wire 32 L instruction [31:0] $end
$var wire 32 M pc_in [31:0] $end
$var integer 32 N i [31:0] $end
$upscope $end
$scope module immediate_module $end
$var wire 32 O instruction [31:0] $end
$var wire 7 P opcode [6:0] $end
$var reg 32 Q immediate_out [31:0] $end
$upscope $end
$scope module main $end
$var wire 7 R opcode [6:0] $end
$var reg 2 S alu_operation [1:0] $end
$var reg 1 6 alu_source $end
$var reg 1 4 branch $end
$var reg 1 / memory_read $end
$var reg 1 . memory_register $end
$var reg 1 - memory_write $end
$var reg 1 ' register_write $end
$upscope $end
$scope module pc_adder $end
$var wire 32 T add_out [31:0] $end
$var wire 32 U add_in [31:0] $end
$upscope $end
$scope module pc_reg $end
$var wire 1 " clock $end
$var wire 32 V pc_in [31:0] $end
$var wire 1 # reset $end
$var reg 32 W pc_out [31:0] $end
$upscope $end
$scope module register $end
$var wire 1 " clock $end
$var wire 32 X data_in [31:0] $end
$var wire 32 Y instruction [31:0] $end
$var wire 1 ' write_enable $end
$var wire 5 Z dest_add [4:0] $end
$var wire 32 [ data_2 [31:0] $end
$var wire 32 \ data_1 [31:0] $end
$var wire 5 ] add_2 [4:0] $end
$var wire 5 ^ add_1 [4:0] $end
$var integer 32 _ i [31:0] $end
$upscope $end
$upscope $end
$upscope $end
$enddefinitions $end
$comment Show the parameter values. $end
$dumpall
$end
#0
$dumpvars
b100000 _
bx ^
bx ]
bx \
bx [
bx Z
bx Y
bx X
bx W
bx V
bx U
bx T
bx S
bx R
bx Q
bx P
bx O
b100000000 N
bx M
bx L
b100000000 K
bx J
bx I
bx H
bx G
bx F
bx E
bx D
bx C
bx B
bx A
x@
bx ?
bx >
bx =
bx <
bx ;
bx :
bx 9
bx 8
bx 7
x6
x5
x4
x3
bx 2
bx 1
bx 0
x/
x.
x-
bx ,
bx +
bx *
bx )
bx (
x'
bx &
bx %
bx $
1#
0"
bx !
$end
#5000
b0 (
b0 X
15
b0 !
b0 $
b0 7
b0 >
b0 H
b0 9
b0 ;
b0 2
b0 J
b0 &
b0 <
b0 G
b0 \
b0 %
b0 F
b0 I
b0 [
03
0'
06
0-
b0 8
b0 B
b0 S
0.
0/
04
b100 *
b100 V
b0 P
b0 ^
b0 ]
b0 Z
b0 E
0@
b0 A
b0 R
b0 :
b0 =
b0 C
b0 +
b0 1
b0 Q
b0 0
b0 ?
b0 D
b0 L
b0 O
b0 Y
b100 )
b100 T
b0 ,
b0 M
b0 U
b0 W
1"
#10000
0"
#15000
1"
#20000
0"
0#
#25000
b1000 *
b1000 V
b1000 )
b1000 T
b100 +
b100 ,
b100 M
b100 U
b100 W
1"
#30000
0"
#35000
b1100 *
b1100 V
b1100 )
b1100 T
b1000 +
b1000 ,
b1000 M
b1000 U
b1000 W
1"
#40000
0"
#45000
b10000 *
b10000 V
b10000 )
b10000 T
b1100 +
b1100 ,
b1100 M
b1100 U
b1100 W
1"
#50000
0"
#55000
b10100 *
b10100 V
b10100 )
b10100 T
b10000 +
b10000 ,
b10000 M
b10000 U
b10000 W
1"
#60000
0"
#65000
b11000 *
b11000 V
b11000 )
b11000 T
b10100 +
b10100 ,
b10100 M
b10100 U
b10100 W
1"
#70000
0"
#75000
b11100 *
b11100 V
b11100 )
b11100 T
b11000 +
b11000 ,
b11000 M
b11000 U
b11000 W
1"
#80000
0"
#85000
b100000 *
b100000 V
b100000 )
b100000 T
b11100 +
b11100 ,
b11100 M
b11100 U
b11100 W
1"
#90000
0"
#95000
b100100 *
b100100 V
b100100 )
b100100 T
b100000 +
b100000 ,
b100000 M
b100000 U
b100000 W
1"
#100000
0"
#105000
b101000 *
b101000 V
b101000 )
b101000 T
b100100 +
b100100 ,
b100100 M
b100100 U
b100100 W
1"
#110000
0"
#115000
b101100 *
b101100 V
b101100 )
b101100 T
b101000 +
b101000 ,
b101000 M
b101000 U
b101000 W
1"
#120000
0"
#125000
b110000 *
b110000 V
b110000 )
b110000 T
b101100 +
b101100 ,
b101100 M
b101100 U
b101100 W
1"
#130000
0"
#135000
b110100 *
b110100 V
b110100 )
b110100 T
b110000 +
b110000 ,
b110000 M
b110000 U
b110000 W
1"
#140000
0"
#145000
b111000 *
b111000 V
b111000 )
b111000 T
b110100 +
b110100 ,
b110100 M
b110100 U
b110100 W
1"
#150000
0"
#155000
b111100 *
b111100 V
b111100 )
b111100 T
b111000 +
b111000 ,
b111000 M
b111000 U
b111000 W
1"
#160000
0"
#165000
b1000000 *
b1000000 V
b1000000 )
b1000000 T
b111100 +
b111100 ,
b111100 M
b111100 U
b111100 W
1"
#170000
0"
#175000
b1000100 *
b1000100 V
b1000100 )
b1000100 T
b1000000 +
b1000000 ,
b1000000 M
b1000000 U
b1000000 W
1"
#180000
0"
#185000
b1001000 *
b1001000 V
b1001000 )
b1001000 T
b1000100 +
b1000100 ,
b1000100 M
b1000100 U
b1000100 W
1"
#190000
0"
#195000
b1001100 *
b1001100 V
b1001100 )
b1001100 T
b1001000 +
b1001000 ,
b1001000 M
b1001000 U
b1001000 W
1"
#200000
0"
#205000
b1010000 *
b1010000 V
b1010000 )
b1010000 T
b1001100 +
b1001100 ,
b1001100 M
b1001100 U
b1001100 W
1"
#210000
0"
#215000
b1010100 *
b1010100 V
b1010100 )
b1010100 T
b1010000 +
b1010000 ,
b1010000 M
b1010000 U
b1010000 W
1"
